document_classification/__init__.py
document_classification/common/__init__.py
document_classification/common/exceptions/__init__.py
document_classification/common/exceptions/base_error.py
document_classification/common/parsers/__init__.py
document_classification/common/parsers/default_parser.py
document_classification/common/parsers/interfaces.py
document_classification/common/parsers/layout_preserving_formatter.py
document_classification/common/parsers/parse_and_format.py
document_classification/common/parsers/pydantic_models.py
document_classification/common/schemas/__init__.py
document_classification/common/schemas/bounding_box.py
document_classification/common/utils/__init__.py
document_classification/common/utils/dataframe_to_text.py
document_classification/common/utils/file_utils.py
document_classification/common/utils/get_device.py
document_classification/common/utils/json_loader.py
document_classification/common/utils/json_to_ocr_text.py
document_classification/common/utils/pdf_images.py
document_classification/common/utils/rotate.py
document_classification/fasttext_model/__init__.py
document_classification/fasttext_model/evaluate/__init__.py
document_classification/fasttext_model/evaluate/evaluate.py
document_classification/fasttext_model/predictor/__init__.py
document_classification/fasttext_model/predictor/predictor.py
document_classification/fasttext_model/text_preprocessor.py
document_classification/fasttext_model/train/__init__.py
document_classification/fasttext_model/train/create_dataset.py
document_classification/fasttext_model/train/train.py
document_classification/language_model/__init__.py
document_classification/language_model/config.py
document_classification/language_model/dataset_preparer/__init__.py
document_classification/language_model/dataset_preparer/base.py
document_classification/language_model/dataset_preparer/custom_collate_function.py
document_classification/language_model/dataset_preparer/text_only.py
document_classification-0.1.0.dist-info/METADATA
document_classification-0.1.0.dist-info/WHEEL
document_classification-0.1.0.dist-info/RECORD
