Metadata-Version: 2.1
Name: document-classification
Version: 0.1.0
Summary: Awesome document classifcation - Implementation of major techniques
License: MIT
Author: Amit Timalsina
Author-email: amittimalsina14@gmail.com
Requires-Python: >=3.10,<4.0
Classifier: License :: OSI Approved :: MIT License
Classifier: Programming Language :: Python :: 3
Classifier: Programming Language :: Python :: 3.10
Classifier: Programming Language :: Python :: 3.11
Classifier: Programming Language :: Python :: 3.12
Classifier: Programming Language :: Python :: 3.13
Requires-Dist: albumentations (>=1.4.18,<2.0.0)
Requires-Dist: fasttext (>=0.9.3,<0.10.0)
Requires-Dist: google (>=3.0.0,<4.0.0)
Requires-Dist: google-cloud-vision (>=3.7.4,<4.0.0)
Requires-Dist: instructor (>=1.6.3,<2.0.0)
Requires-Dist: langsmith (>=0.1.139,<0.2.0)
Requires-Dist: loguru (>=0.7.2,<0.8.0)
Requires-Dist: paddleocr (>=2.9.0,<3.0.0)
Requires-Dist: paddlepaddle (>=2.6.2,<3.0.0)
Requires-Dist: pandas (>=2.2.3,<3.0.0)
Requires-Dist: pydantic (>=2.7.0,<3.0.0)
Requires-Dist: torch (>=2.5.1,<3.0.0)
